stactools/landsat/__init__.py
stactools/landsat/ang_metadata.py
stactools/landsat/commands.py
stactools/landsat/constants.py
stactools/landsat/mtl_metadata.py
stactools/landsat/stac.py
stactools/landsat/utils.py
stactools/landsat/fragments/__init__.py
stactools/landsat/fragments/collections/landsat-c2-l1.json
stactools/landsat/fragments/collections/landsat-c2-l2.json
stactools/landsat/fragments/common/common-assets.json
stactools/landsat/fragments/etm/sr-assets.json
stactools/landsat/fragments/etm/sr-eo-bands.json
stactools/landsat/fragments/etm/sr-raster-bands.json
stactools/landsat/fragments/etm/st-assets.json
stactools/landsat/fragments/etm/st-eo-bands.json
stactools/landsat/fragments/etm/st-raster-bands.json
stactools/landsat/fragments/mss/sr-assets.json
stactools/landsat/fragments/mss/sr-eo-bands.json
stactools/landsat/fragments/mss/sr-raster-bands.json
stactools/landsat/fragments/oli_tirs/sr-assets.json
stactools/landsat/fragments/oli_tirs/sr-eo-bands.json
stactools/landsat/fragments/oli_tirs/sr-raster-bands.json
stactools/landsat/fragments/oli_tirs/st-assets.json
stactools/landsat/fragments/oli_tirs/st-eo-bands.json
stactools/landsat/fragments/oli_tirs/st-raster-bands.json
stactools/landsat/fragments/tm/sr-assets.json
stactools/landsat/fragments/tm/sr-eo-bands.json
stactools/landsat/fragments/tm/sr-raster-bands.json
stactools/landsat/fragments/tm/st-assets.json
stactools/landsat/fragments/tm/st-eo-bands.json
stactools/landsat/fragments/tm/st-raster-bands.json
stactools_landsat-0.5.0.dist-info/LICENSE
stactools_landsat-0.5.0.dist-info/METADATA
stactools_landsat-0.5.0.dist-info/WHEEL
stactools_landsat-0.5.0.dist-info/top_level.txt
stactools_landsat-0.5.0.dist-info/RECORD
