Metadata-Version: 2.1
Name: stactools-landsat
Version: 0.5.0
Summary: stactools package for Landsat data
Home-page: https://github.com/stactools-packages/landsat
Author: stac-utils
Author-email: stac@radiant.earth
Project-URL: Issues, https://github.com/stactools-packages/landsat/issues
Keywords: stactools,pystac,catalog,STAC,Landsat
Classifier: Development Status :: 4 - Beta
Classifier: License :: OSI Approved :: Apache Software License
Classifier: Programming Language :: Python :: 3.8
Classifier: Programming Language :: Python :: 3.9
Classifier: Programming Language :: Python :: 3.10
License-File: LICENSE
Requires-Dist: stactools >=0.4.2
Requires-Dist: pystac-client >=0.5.1
